<?xml version="1.0" encoding="utf-8" ?>
<dwsync>
<file name="DiscISAM.php" server="23.20.75.160//var/www/G095RC/" local="130153758460000000" remote="130153758460000000" />
<file name="MemoryGZip.php" server="23.20.75.160//var/www/G095RC/" local="130153758470000000" remote="130153758470000000" />
<file name="Wincache.php" server="23.20.75.160//var/www/G095RC/" local="130153758480000000" remote="130153758480000000" />
<file name="APC.php" server="23.20.75.160//var/www/G095RC/" local="130153758450000000" remote="130153758450000000" />
<file name="ICache.php" server="23.20.75.160//var/www/G095RC/" local="130153758460000000" remote="130153758460000000" />
<file name="PHPTemp.php" server="23.20.75.160//var/www/G095RC/" local="130153758480000000" remote="130153758480000000" />
<file name="Memory.php" server="23.20.75.160//var/www/G095RC/" local="130153758470000000" remote="130153758470000000" />
<file name="Memcache.php" server="23.20.75.160//var/www/G095RC/" local="130153758460000000" remote="130153758460000000" />
<file name="CacheBase.php" server="23.20.75.160//var/www/G095RC/" local="130153758450000000" remote="130153758450000000" />
<file name="MemorySerialized.php" server="23.20.75.160//var/www/G095RC/" local="130153758480000000" remote="130153758480000000" />
<file name="APC.php" server="64.183.41.50:8022//var/www/cateringservices4u/" local="130208800420000000" remote="130208800420000000" />
<file name="CacheBase.php" server="64.183.41.50:8022//var/www/cateringservices4u/" local="130208800430000000" remote="130208800430000000" />
<file name="DiscISAM.php" server="64.183.41.50:8022//var/www/cateringservices4u/" local="130208800430000000" remote="130208800430000000" />
<file name="ICache.php" server="64.183.41.50:8022//var/www/cateringservices4u/" local="130208800430000000" remote="130208800430000000" />
<file name="Memcache.php" server="64.183.41.50:8022//var/www/cateringservices4u/" local="130208800430000000" remote="130208800430000000" />
<file name="Memory.php" server="64.183.41.50:8022//var/www/cateringservices4u/" local="130208800430000000" remote="130208800430000000" />
<file name="MemoryGZip.php" server="64.183.41.50:8022//var/www/cateringservices4u/" local="130208800440000000" remote="130208800440000000" />
<file name="MemorySerialized.php" server="64.183.41.50:8022//var/www/cateringservices4u/" local="130208800440000000" remote="130208800440000000" />
<file name="PHPTemp.php" server="64.183.41.50:8022//var/www/cateringservices4u/" local="130208800440000000" remote="130208800440000000" />
<file name="Wincache.php" server="64.183.41.50:8022//var/www/cateringservices4u/" local="130208800440000000" remote="130208800440000000" />
</dwsync>