<?xml version="1.0" encoding="utf-8" ?>
<dwsync>
<file name="logo_example.jpg" server="23.20.75.160//var/www/G095RC/" local="130149256510000000" remote="130149256510000000" />
<file name="tcpdf_logo.jpg" server="23.20.75.160//var/www/G095RC/" local="130149256530000000" remote="130149256530000000" />
<file name="_blank.png" server="23.20.75.160//var/www/G095RC/" local="130149256550000000" remote="130149256550000000" />
<file name="logo_example.gif" server="23.20.75.160//var/www/G095RC/" local="130149256510000000" remote="130149256510000000" />
<file name="image_demo.jpg" server="23.20.75.160//var/www/G095RC/" local="130149256490000000" remote="130149256490000000" />
<file name="tux.svg" server="23.20.75.160//var/www/G095RC/" local="130149256550000000" remote="130149256550000000" />
<file name="tiger.ai" server="23.20.75.160//var/www/G095RC/" local="130149256540000000" remote="130149256540000000" />
<file name="logo_example.png" server="23.20.75.160//var/www/G095RC/" local="130149256520000000" remote="130149256520000000" />
<file name="img.png" server="23.20.75.160//var/www/G095RC/" local="130149256500000000" remote="130149256500000000" />
<file name="pelican.ai" server="23.20.75.160//var/www/G095RC/" local="130149256520000000" remote="130149256520000000" />
<file name="alpha.png" server="23.20.75.160//var/www/G095RC/" local="130149256460000000" remote="130149256460000000" />
<file name="tcpdf_cell.png" server="23.20.75.160//var/www/G095RC/" local="130149256520000000" remote="130149256520000000" />
<file name="testsvg.svg" server="23.20.75.160//var/www/G095RC/" local="130149256540000000" remote="130149256540000000" />
<file name="image_with_alpha.png" server="23.20.75.160//var/www/G095RC/" local="130149256500000000" remote="130149256500000000" />
<file name="tcpdf_signature.png" server="23.20.75.160//var/www/G095RC/" local="130149256530000000" remote="130149256530000000" />
<file name="bug.eps" server="23.20.75.160//var/www/G095RC/" local="130149256470000000" remote="130149256470000000" />
<file name="alpha.png" server="64.183.41.50:8022//var/www/cateringservices4u/" local="130208801580000000" remote="130208801580000000" />
<file name="bug.eps" server="64.183.41.50:8022//var/www/cateringservices4u/" local="130208801580000000" remote="130208801580000000" />
<file name="image_demo.jpg" server="64.183.41.50:8022//var/www/cateringservices4u/" local="130208801590000000" remote="130208801590000000" />
<file name="image_with_alpha.png" server="64.183.41.50:8022//var/www/cateringservices4u/" local="130208801600000000" remote="130208801600000000" />
<file name="img.png" server="64.183.41.50:8022//var/www/cateringservices4u/" local="130208801600000000" remote="130208801600000000" />
<file name="logo_example.gif" server="64.183.41.50:8022//var/www/cateringservices4u/" local="130208801600000000" remote="130208801600000000" />
<file name="logo_example.jpg" server="64.183.41.50:8022//var/www/cateringservices4u/" local="130208801600000000" remote="130208801600000000" />
<file name="logo_example.png" server="64.183.41.50:8022//var/www/cateringservices4u/" local="130208801610000000" remote="130208801610000000" />
<file name="pelican.ai" server="64.183.41.50:8022//var/www/cateringservices4u/" local="130208801610000000" remote="130208801610000000" />
<file name="tcpdf_cell.png" server="64.183.41.50:8022//var/www/cateringservices4u/" local="130208801610000000" remote="130208801610000000" />
<file name="tcpdf_logo.jpg" server="64.183.41.50:8022//var/www/cateringservices4u/" local="130208801610000000" remote="130208801610000000" />
<file name="tcpdf_signature.png" server="64.183.41.50:8022//var/www/cateringservices4u/" local="130208801610000000" remote="130208801610000000" />
<file name="testsvg.svg" server="64.183.41.50:8022//var/www/cateringservices4u/" local="130208801610000000" remote="130208801610000000" />
<file name="tiger.ai" server="64.183.41.50:8022//var/www/cateringservices4u/" local="130208801620000000" remote="130208801620000000" />
<file name="tux.svg" server="64.183.41.50:8022//var/www/cateringservices4u/" local="130208801620000000" remote="130208801620000000" />
<file name="_blank.png" server="64.183.41.50:8022//var/www/cateringservices4u/" local="130208801620000000" remote="130208801620000000" />
</dwsync>