<?xml version="1.0" encoding="utf-8" ?>
<dwsync>
<file name="ui-bg_glass_55_fbf9ee_1x400.png" server="23.20.75.160//var/www/G095RC/" local="130153755740000000" remote="130153755740000000" />
<file name="ui-bg_glass_75_dadada_1x400.png" server="23.20.75.160//var/www/G095RC/" local="130153755750000000" remote="130153755750000000" />
<file name="ui-icons_cd0a0a_256x240.png" server="23.20.75.160//var/www/G095RC/" local="130153755790000000" remote="130153755790000000" />
<file name="ui-bg_inset-soft_95_fef1ec_1x100.png" server="23.20.75.160//var/www/G095RC/" local="130153755760000000" remote="130153755760000000" />
<file name="ui-bg_highlight-soft_75_cccccc_1x100.png" server="23.20.75.160//var/www/G095RC/" local="130153755760000000" remote="130153755760000000" />
<file name="ui-icons_222222_256x240.png" server="23.20.75.160//var/www/G095RC/" local="130153755770000000" remote="130153755770000000" />
<file name="ui-bg_flat_0_aaaaaa_40x100.png" server="23.20.75.160//var/www/G095RC/" local="130153755740000000" remote="130153755740000000" />
<file name="ui-icons_454545_256x240.png" server="23.20.75.160//var/www/G095RC/" local="130153755780000000" remote="130153755780000000" />
<file name="ui-bg_glass_75_e6e6e6_1x400.png" server="23.20.75.160//var/www/G095RC/" local="130153755750000000" remote="130153755750000000" />
<file name="ui-bg_glass_65_ffffff_1x400.png" server="23.20.75.160//var/www/G095RC/" local="130153755740000000" remote="130153755740000000" />
<file name="ui-bg_glass_75_ffffff_1x400.png" server="23.20.75.160//var/www/G095RC/" local="130153755760000000" remote="130153755760000000" />
<file name="ui-icons_2e83ff_256x240.png" server="23.20.75.160//var/www/G095RC/" local="130153755780000000" remote="130153755780000000" />
<file name="ui-icons_888888_256x240.png" server="23.20.75.160//var/www/G095RC/" local="130153755790000000" remote="130153755790000000" />
<file name="ui-bg_flat_0_aaaaaa_40x100.png" server="64.183.41.50:8022//var/www/cateringservices4u/" local="130208799540000000" remote="130208799540000000" />
<file name="ui-bg_glass_55_fbf9ee_1x400.png" server="64.183.41.50:8022//var/www/cateringservices4u/" local="130208799550000000" remote="130208799550000000" />
<file name="ui-bg_glass_65_ffffff_1x400.png" server="64.183.41.50:8022//var/www/cateringservices4u/" local="130208799550000000" remote="130208799550000000" />
<file name="ui-bg_glass_75_dadada_1x400.png" server="64.183.41.50:8022//var/www/cateringservices4u/" local="130208799550000000" remote="130208799550000000" />
<file name="ui-bg_glass_75_e6e6e6_1x400.png" server="64.183.41.50:8022//var/www/cateringservices4u/" local="130208799550000000" remote="130208799550000000" />
<file name="ui-bg_glass_75_ffffff_1x400.png" server="64.183.41.50:8022//var/www/cateringservices4u/" local="130208799550000000" remote="130208799550000000" />
<file name="ui-bg_highlight-soft_75_cccccc_1x100.png" server="64.183.41.50:8022//var/www/cateringservices4u/" local="130208799550000000" remote="130208799550000000" />
<file name="ui-bg_inset-soft_95_fef1ec_1x100.png" server="64.183.41.50:8022//var/www/cateringservices4u/" local="130208799550000000" remote="130208799550000000" />
<file name="ui-icons_222222_256x240.png" server="64.183.41.50:8022//var/www/cateringservices4u/" local="130208799550000000" remote="130208799550000000" />
<file name="ui-icons_2e83ff_256x240.png" server="64.183.41.50:8022//var/www/cateringservices4u/" local="130208799550000000" remote="130208799550000000" />
<file name="ui-icons_454545_256x240.png" server="64.183.41.50:8022//var/www/cateringservices4u/" local="130208799560000000" remote="130208799560000000" />
<file name="ui-icons_888888_256x240.png" server="64.183.41.50:8022//var/www/cateringservices4u/" local="130208799560000000" remote="130208799560000000" />
<file name="ui-icons_cd0a0a_256x240.png" server="64.183.41.50:8022//var/www/cateringservices4u/" local="130208799560000000" remote="130208799560000000" />
</dwsync>